[null,{"id":1,"autoRemovalTiming":0,"chanceByDamage":100,"iconIndex":1,"maxTurns":1,"message1":"fell down!","message2":"I defeated it!","message3":"","message4":"stood up!","minTurns":1,"motion":3,"name":"Unable to fight","note":"<state help>\nIncapable of combat: unable to take any actions\n</state help>\nState 1 is when HP becomes 0\nIt will be added automatically.","overlay":0,"priority":100,"releaseByDamage":false,"removeAtBattleEnd":false,"removeByDamage":false,"removeByRestriction":false,"removeByWalking":false,"restriction":4,"stepsToRemove":100,"traits":[{"code":23,"dataId":9,"value":0}]},{"id":2,"autoRemovalTiming":2,"chanceByDamage":100,"description":"","iconIndex":0,"maxTurns":1,"message1":"","message2":"","message3":"","message4":"","minTurns":1,"motion":0,"name":"defense","note":"","overlay":0,"priority":0,"removeAtBattleEnd":true,"removeByDamage":false,"removeByRestriction":true,"removeByWalking":false,"restriction":0,"stepsToRemove":100,"traits":[{"code":62,"dataId":1,"value":0}]},{"id":3,"autoRemovalTiming":0,"chanceByDamage":100,"description":"","iconIndex":0,"maxTurns":1,"message1":"","message2":"","message3":"","message4":"","minTurns":1,"motion":0,"name":"immortality","note":"","overlay":0,"priority":0,"removeAtBattleEnd":true,"removeByDamage":false,"removeByRestriction":false,"removeByWalking":false,"restriction":0,"stepsToRemove":100,"traits":[{"code":14,"dataId":1,"value":0}]},{"id":4,"autoRemovalTiming":1,"chanceByDamage":100,"iconIndex":2,"maxTurns":3,"message1":"is poisoned!","message2":"I poisoned it!","message3":"","message4":"The poison is gone!","minTurns":3,"motion":1,"overlay":1,"name":"poison","note":"<state help>\nPoison: HP decreases by 10% every turn\n</state help>","priority":50,"releaseByDamage":false,"removeAtBattleEnd":true,"removeByDamage":false,"removeByRestriction":false,"removeByWalking":false,"restriction":0,"stepsToRemove":100,"traits":[{"code":22,"dataId":7,"value":-0.1}]},{"id":5,"autoRemovalTiming":1,"chanceByDamage":50,"iconIndex":6,"maxTurns":3,"message1":"I was confused!","message2":"Confused!","message3":"","message4":"I came to my senses!","minTurns":3,"motion":1,"name":"confusion","note":"<state help>\nConfusion: Attack randomly regardless of friend or foe.\n</state help>","overlay":5,"priority":75,"releaseByDamage":false,"removeAtBattleEnd":true,"removeByDamage":true,"removeByRestriction":false,"removeByWalking":false,"restriction":2,"stepsToRemove":100,"traits":[]},{"id":6,"autoRemovalTiming":1,"chanceByDamage":75,"iconIndex":8,"maxTurns":3,"message1":"fell asleep!","message2":"I put him to sleep!","message3":"","message4":"I woke up!","minTurns":3,"motion":2,"name":"sleep","note":"<state help>\nSleep: Incapable of action until canceled\n</state help>","overlay":7,"priority":90,"releaseByDamage":true,"removeAtBattleEnd":true,"removeByDamage":true,"removeByRestriction":false,"removeByWalking":false,"restriction":4,"stepsToRemove":100,"traits":[{"code":22,"dataId":1,"value":-1}]},{"id":7,"autoRemovalTiming":1,"chanceByDamage":50,"iconIndex":7,"maxTurns":3,"message1":"was fascinated!","message2":"It fascinated me!","message3":"","message4":"I came to my senses!","minTurns":3,"motion":1,"name":"Fascinating","note":"<state help>\nCharm: Attack allies\n</state help>","overlay":6,"priority":80,"releaseByDamage":false,"removeAtBattleEnd":true,"removeByDamage":true,"removeByRestriction":false,"removeByWalking":false,"restriction":3,"stepsToRemove":100,"traits":[]},{"id":8,"autoRemovalTiming":1,"chanceByDamage":100,"iconIndex":4,"maxTurns":3,"message1":"was silent!","message2":"silenced!","message3":"","message4":"The silence has been lifted!","minTurns":3,"motion":1,"name":"silence","note":"<state help>\nSilence: All magic is prohibited.\n</state help>","overlay":3,"priority":65,"releaseByDamage":false,"removeAtBattleEnd":true,"removeByDamage":false,"removeByRestriction":false,"removeByWalking":false,"restriction":0,"stepsToRemove":100,"traits":[{"code":42,"dataId":1,"value":0}]},{"id":9,"autoRemovalTiming":1,"chanceByDamage":100,"iconIndex":28,"maxTurns":3,"message1":"is no longer affected by status abnormalities!","message2":"is no longer affected by status abnormalities!","message3":"","message4":"'s status ailment resistance has returned to normal!","minTurns":3,"motion":1,"name":"Disable status abnormality","note":"<state help>\nNullify status ailments: Disable all status ailments\n</state help>","overlay":3,"priority":65,"releaseByDamage":false,"removeAtBattleEnd":true,"removeByDamage":false,"removeByRestriction":false,"removeByWalking":false,"restriction":0,"stepsToRemove":100,"traits":[{"code":14,"dataId":4,"value":1},{"code":14,"dataId":5,"value":1},{"code":14,"dataId":6,"value":1},{"code":14,"dataId":7,"value":1},{"code":14,"dataId":8,"value":1}]},{"id":10,"autoRemovalTiming":1,"chanceByDamage":100,"iconIndex":11,"maxTurns":2,"message1":"His combat skills were sealed!","message2":"'s combat techniques have been sealed!","message3":"","message4":"The seal has been broken!","minTurns":2,"motion":1,"name":"Battle technique seal","note":"<state help>\nCombat Skills Seal: Prohibits use of all combat skills\n</state help>","overlay":3,"priority":65,"releaseByDamage":false,"removeAtBattleEnd":true,"removeByDamage":false,"removeByRestriction":false,"removeByWalking":false,"restriction":0,"stepsToRemove":100,"traits":[{"code":42,"dataId":2,"value":1}]},{"id":11,"autoRemovalTiming":2,"chanceByDamage":75,"traits":[],"iconIndex":0,"maxTurns":3,"message1":"","message2":"","message3":"","message4":"","minTurns":2,"motion":0,"name":"Anomaly","note":"For performances in the dragon's bed.\nLeave messages etc. blank so that the existence of the state is not visible.","overlay":0,"priority":10,"removeAtBattleEnd":true,"removeByDamage":false,"removeByRestriction":false,"removeByWalking":false,"restriction":4,"stepsToRemove":100},{"id":12,"autoRemovalTiming":0,"chanceByDamage":75,"traits":[],"iconIndex":0,"maxTurns":3,"message1":"","message2":"","message3":"","message4":"","minTurns":2,"motion":0,"name":"No contents","note":"","overlay":0,"priority":50,"removeAtBattleEnd":false,"removeByDamage":false,"removeByRestriction":false,"removeByWalking":false,"restriction":0,"stepsToRemove":100},{"id":13,"autoRemovalTiming":2,"chanceByDamage":100,"iconIndex":78,"maxTurns":3,"message1":"prepared for a counterattack!","message2":"prepared for a counterattack!","message3":"","message4":"released his counterattack stance.","minTurns":3,"motion":1,"overlay":0,"name":"counterattack","note":"*For later use\n<state help>\nCounterattack: Immediately counterattack when attacked\n</state help>\n<CE_MagicCounter:100>\n↑100% counterattack when receiving magic attack\n<CE_CounterSkillId:114>","priority":50,"releaseByDamage":false,"removeAtBattleEnd":true,"removeByDamage":false,"removeByRestriction":true,"removeByWalking":false,"restriction":0,"stepsToRemove":100,"traits":[{"code":22,"dataId":6,"value":1},{"code":22,"dataId":0,"value":0.15}]},{"id":14,"autoRemovalTiming":2,"chanceByDamage":100,"iconIndex":78,"maxTurns":3,"message1":"prepared for a counterattack!","message2":"prepared for a counterattack!","message3":"","message4":"released his counterattack stance.","minTurns":3,"motion":1,"overlay":0,"name":"counterattack","note":"※After the end/Niyo\n<state help>\nCounterattack: Immediately counterattack when attacked\n</state help>\n<CE_MagicCounter:100>\n↑100% counterattack when receiving magic attack\n<CE_CounterSkillId:115>","priority":50,"releaseByDamage":false,"removeAtBattleEnd":true,"removeByDamage":false,"removeByRestriction":true,"removeByWalking":false,"restriction":0,"stepsToRemove":100,"traits":[{"code":22,"dataId":6,"value":1},{"code":22,"dataId":0,"value":0.15}]},{"id":15,"autoRemovalTiming":1,"chanceByDamage":100,"traits":[],"iconIndex":12,"maxTurns":1,"message1":"is preparing to attack!","message2":"is preparing to attack!","message3":"","message4":"Preparations for attack have been released!","minTurns":1,"motion":0,"name":"preparation for attack","note":"<state help>\nPreparation for attack: A powerful technique will be activated on the next turn.\n</state help>","overlay":0,"priority":70,"removeAtBattleEnd":true,"removeByDamage":false,"removeByRestriction":false,"removeByWalking":false,"restriction":0,"stepsToRemove":100},{"id":16,"autoRemovalTiming":2,"chanceByDamage":100,"iconIndex":78,"maxTurns":3,"message1":"prepared for a counterattack!","message2":"prepared for a counterattack!","message3":"","message4":"released his counterattack stance.","minTurns":3,"motion":1,"overlay":0,"name":"counterattack","note":"* (enemy) for the next one\n<state help>\nCounterattack: Immediately counterattack when attacked\n</state help>\n<CE_MagicCounter:100>\n↑100% counterattack when receiving magic attack\n<CE_CounterSkillId:42>","priority":50,"releaseByDamage":false,"removeAtBattleEnd":true,"removeByDamage":false,"removeByRestriction":true,"removeByWalking":false,"restriction":0,"stepsToRemove":100,"traits":[{"code":22,"dataId":6,"value":1}]},{"id":17,"autoRemovalTiming":0,"chanceByDamage":100,"iconIndex":90,"maxTurns":3,"message1":"","message2":"","message3":"","message4":"Washed off the leakage!","minTurns":3,"motion":1,"overlay":0,"name":"Peeing","note":"<state help>\nWetting: AGI and accuracy reduction\n</state help>","priority":45,"releaseByDamage":false,"removeAtBattleEnd":false,"removeByDamage":false,"removeByRestriction":false,"removeByWalking":false,"restriction":0,"stepsToRemove":100,"traits":[{"code":21,"dataId":6,"value":0.5},{"code":22,"dataId":0,"value":-0.3}]},{"id":18,"autoRemovalTiming":0,"chanceByDamage":100,"iconIndex":91,"maxTurns":3,"message1":"","message2":"","message3":"","message4":"The cloudy liquid was washed away!","minTurns":3,"motion":1,"overlay":0,"name":"Bukkake","note":"<state help>\nBukkake: Combat techniques cannot be used.\n</state help>\n\nThe message field is blank.\n(It will be displayed separately by inputting Common Ev text)","priority":45,"releaseByDamage":false,"removeAtBattleEnd":false,"removeByDamage":false,"removeByRestriction":false,"removeByWalking":false,"restriction":0,"stepsToRemove":100,"traits":[{"code":42,"dataId":2,"value":1}]},{"id":19,"autoRemovalTiming":0,"chanceByDamage":100,"traits":[],"iconIndex":0,"maxTurns":1,"message1":"","message2":"","message3":"","message4":"","minTurns":1,"motion":0,"name":"","note":"","overlay":0,"priority":50,"removeAtBattleEnd":false,"removeByDamage":false,"removeByRestriction":false,"removeByWalking":false,"restriction":0,"stepsToRemove":100},{"id":20,"autoRemovalTiming":0,"chanceByDamage":100,"traits":[],"iconIndex":0,"maxTurns":1,"message1":"","message2":"","message3":"","message4":"","minTurns":1,"motion":0,"name":"","note":"","overlay":0,"priority":50,"removeAtBattleEnd":false,"removeByDamage":false,"removeByRestriction":false,"removeByWalking":false,"restriction":0,"stepsToRemove":100}]